ottergon/__init__.py
ottergon/pyproject.toml
ottergon/MANIFEST.in
ottergon/get_path.py
ottergon/setup.py
ottergon/tox.ini
ottergon/ottergon.cpython-38-x86_64-linux-gnu.so
ottergon-0.5.0.data/data/lib/librocketjoe_log.a
ottergon-0.5.0.dist-info/METADATA
ottergon-0.5.0.dist-info/LICENSE
ottergon-0.5.0.dist-info/top_level.txt
ottergon-0.5.0.dist-info/WHEEL
ottergon-0.5.0.dist-info/RECORD
